vimball
