Metadata-Version: 1.1
Name: vimball
Version: 0.5.1
Summary: a command-line vimball archive extractor
Home-page: https://github.com/radhermit/vimball
Author: Tim Harder
Author-email: radhermit@gmail.com
License: MIT
Platform: Posix
Classifier: Intended Audience :: Developers
Classifier: License :: OSI Approved :: MIT License
Classifier: Programming Language :: Python :: 3.3
Classifier: Programming Language :: Python :: 3.4
